twyla/chat/templates/__init__.py
twyla/chat/templates/base.py
twyla/chat/templates/buttons.py
twyla/chat/templates/carousel.py
twyla/chat/templates/generic.py
twyla/chat/templates/image.py
twyla/chat/templates/quickreplies.py
twyla/chat/templates/text.py
twyla_chat_templates-0.1.0.dist-info/LICENSE
twyla_chat_templates-0.1.0.dist-info/WHEEL
twyla_chat_templates-0.1.0.dist-info/METADATA
twyla_chat_templates-0.1.0.dist-info/RECORD
