Metadata-Version: 2.1
Name: twyla-chat-templates
Version: 0.1.0
Summary: A collection of Twyla chat message templates
Home-page: https://github.com/twyla-ai/twyla-chat-templates
License: MIT
Author: Twyla Engineering
Author-email: software@twyla.ai
Requires-Python: >=3.6,<4.0
Classifier: License :: OSI Approved :: MIT License
Classifier: Programming Language :: Python :: 3
Classifier: Programming Language :: Python :: 3.6
Classifier: Programming Language :: Python :: 3.7
Requires-Dist: dataclasses (>=0.6,<0.7); python_version >= "3.6" and python_version < "3.7"
Project-URL: Repository, https://github.com/twyla-ai/twyla-chat-templates
